{
  "265852448": {
    "en": "Saga Prefecture Arita Kami-Arita Station",
    "ja": "佐賀県 有田町 上有田駅"
  },
  "270856548": {
    "en": "Saga Prefecture Arita Meotoishi Station",
    "ja": "佐賀県 有田町 夫婦石駅"
  },
  "270856748": {
    "en": "Saga Prefecture Arita Yamadani Station",
    "ja": "佐賀県 有田町 山谷駅"
  },
  "270857161": {
    "en": "Saga Prefecture Arita NIshi-Arita Station",
    "ja": "佐賀県 有田町 西有田駅"
  },
  "270857171": {
    "en": "Saga Prefecture Arita Midaibashi Station",
    "ja": "佐賀県 有田町 三代橋駅"
  },
  "270857764": {
    "en": "Saga Prefecture Arita Kurogou Station",
    "ja": "佐賀県 有田町 黒川駅"
  },
  "270858225": {
    "en": "Saga Prefecture Arita Oogi Station",
    "ja": "佐賀県 有田町 大木駅"
  },
  "270859700": {
    "en": "Saga Prefecture Arita Zoushuku Station",
    "ja": "佐賀県 有田町 蔵宿駅"
  },
  "6374755514": {
    "en": "Saga Prefecture Arita Arita Station",
    "ja": "佐賀県 有田町 有田駅"
  }
}