{
  "Hyogo Prefecture Nishinomiya Suzaki Station": 346492649,
  "Hyogo Prefecture Nishinomiya Mukogawa Station": 7934875100,
  "Hyogo Prefecture Nishinomiya Mukogawadanchi-Mae Station": 346492697,
  "Hyogo Prefecture Nishinomiya Higashi-Naruo Station": 346492743,
  "Hyogo Prefecture Nishinomiya Mondo-Yakujin Station": 346648359,
  "Hyogo Prefecture Nishinomiya Koyoen Station": 516180759,
  "Hyogo Prefecture Nishinomiya Kurakuenguchi Station": 516180817,
  "Hyogo Prefecture Nishinomiya Shukugawa Station": 3203267292,
  "Hyogo Prefecture Nishinomiya Koshien Station": 3632717539,
  "Hyogo Prefecture Nishinomiya Sakurashukugawa Station": 3905339975,
  "Hyogo Prefecture Nishinomiya Kōshienguchi Station": 3905340859,
  "Hyogo Prefecture Nishinomiya Nishinomiya Station": 7933036754,
  "Hyogo Prefecture Nishinomiya Hanshin-Kokudo Station": 4481776862,
  "Hyogo Prefecture Nishinomiya Nishinomiya-Kitaguchi Station": 6785165713,
  "Hyogo Prefecture Nishinomiya Imazu Station": 7934875091,
  "Hyogo Prefecture Nishinomiya Kōtōen Station": 7196403091,
  "Hyogo Prefecture Nishinomiya Naruo / Mukogawajoshidai-Mae Station": 7933036767,
  "Hyogo Prefecture Nishinomiya Kusugawa Station": 7934875093,
  "Hyogo Prefecture Nishinomiya Koroen Station": 7934894046,
  "Hyogo Prefecture Nishinomiya Nishinomiya-Najio Station": 8018075197,
  "Hyogo Prefecture Nishinomiya Namaze Station": 8018075198
}