{
  "263068970": {
    "en": "Niigata Prefecture Niigata Shinseki Station",
    "ja": "新潟県 新潟市 新関駅"
  },
  "263069803": {
    "en": "Niigata Prefecture Niigata Higashi-Niitsu Station",
    "ja": "新潟県 新潟市 東新津駅"
  },
  "264410551": {
    "en": "Niigata Prefecture Niigata Niizaki Station",
    "ja": "新潟県 新潟市 新崎駅"
  },
  "264413821": {
    "en": "Niigata Prefecture Niigata Niigata Daigaku-mae Station",
    "ja": "新潟県 新潟市 新潟大学前駅"
  },
  "264413827": {
    "en": "Niigata Prefecture Niigata Uchino Station",
    "ja": "新潟県 新潟市 内野駅"
  },
  "264413869": {
    "en": "Niigata Prefecture Niigata Uchino-Nishigaoka Station",
    "ja": "新潟県 新潟市 内野西が丘駅"
  },
  "264413965": {
    "en": "Niigata Prefecture Niigata Maki Station",
    "ja": "新潟県 新潟市 巻駅"
  },
  "264413970": {
    "en": "Niigata Prefecture Niigata Kobari Station",
    "ja": "新潟県 新潟市 小針駅"
  },
  "264414010": {
    "en": "Niigata Prefecture Niigata Iwamuro Station",
    "ja": "新潟県 新潟市 岩室駅"
  },
  "264414094": {
    "en": "Niigata Prefecture Niigata Echigo-Akatsuka Station",
    "ja": "新潟県 新潟市 越後赤塚駅"
  },
  "264414095": {
    "en": "Niigata Prefecture Niigata Echigo-Sone Station",
    "ja": "新潟県 新潟市 越後曽根駅"
  },
  "264414127": {
    "en": "Niigata Prefecture Niigata Aoyama Station",
    "ja": "新潟県 新潟市 青山駅"
  },
  "264414188": {
    "en": "Niigata Prefecture Niigata Terao Station",
    "ja": "新潟県 新潟市 寺尾駅"
  },
  "264800968": {
    "en": "Niigata Prefecture Niigata Niitsu Station",
    "ja": "新潟県 新潟市 新津駅"
  },
  "264801432": {
    "en": "Niigata Prefecture Niigata Kameda Station",
    "ja": "新潟県 新潟市 亀田駅"
  },
  "4087367885": {
    "en": "Niigata Prefecture Niigata Niigata Station",
    "ja": "新潟県 新潟市 新潟駅"
  },
  "4087367886": {
    "en": "Niigata Prefecture Niigata Hakusan Station",
    "ja": "新潟県 新潟市 白山駅"
  },
  "4087367887": {
    "en": "Niigata Prefecture Niigata Sekiya Station",
    "ja": "新潟県 新潟市 関屋駅"
  },
  "4087716008": {
    "en": "Niigata Prefecture Niigata Echigo-Ishiyama Station",
    "ja": "新潟県 新潟市 越後石山駅"
  },
  "4087788338": {
    "en": "Niigata Prefecture Niigata Ogata Station",
    "ja": "新潟県 新潟市 大形駅"
  },
  "4087788339": {
    "en": "Niigata Prefecture Niigata Higashi-Niigata Station",
    "ja": "新潟県 新潟市 東新潟駅"
  },
  "4358958785": {
    "en": "Niigata Prefecture Niigata Ogikawa Station",
    "ja": "新潟県 新潟市 荻川駅"
  },
  "4358958787": {
    "en": "Niigata Prefecture Niigata Satsukino Station",
    "ja": "新潟県 新潟市 さつき野駅"
  },
  "4358959791": {
    "en": "Niigata Prefecture Niigata Furutsu Station",
    "ja": "新潟県 新潟市 古津駅"
  },
  "4358959890": {
    "en": "Niigata Prefecture Niigata Yashiroda Station",
    "ja": "新潟県 新潟市 矢代田駅"
  },
  "4621752486": {
    "en": "Niigata Prefecture Niigata Toyosaka Station",
    "ja": "新潟県 新潟市 豊栄駅"
  },
  "4660003130": {
    "en": "Niigata Prefecture Niigata Hayadori Station",
    "ja": "新潟県 新潟市 早通駅"
  },
  "4660003135": {
    "en": "Niigata Prefecture Niigata Kuroyama Station",
    "ja": "新潟県 新潟市 黒山駅"
  },
  "6039349189": {
    "en": "Niigata Prefecture Niigata Niigata Freight Terminal Station",
    "ja": "新潟県 新潟市 新潟貨物ターミナル駅"
  }
}