{
  "Kyoto Prefecture Nakagyo Ward Nijo Station": 7783352309,
  "Kyoto Prefecture Nakagyo Ward Karasuma Oike Station": 6565091981,
  "Kyoto Prefecture Nakagyo Ward Emmachi Station": 6877587461,
  "Kyoto Prefecture Nakagyo Ward Sai Station": 7126810671,
  "Kyoto Prefecture Nakagyo Ward Nishioji-oike Station": 7744316244,
  "Kyoto Prefecture Nakagyo Ward Marutamachi Station": 7780637513,
  "Kyoto Prefecture Nakagyo Ward Nijojo-mae Station": 7783352310,
  "Kyoto Prefecture Nakagyo Ward Kyoto Shiyakusho-mae Station": 7783352311
}