{
  "青森県 深浦町 追良瀬駅": 264225488,
  "青森県 深浦町 広戸駅": 264225491,
  "青森県 深浦町 大戸瀬駅": 264225492,
  "青森県 深浦町 風合瀬駅": 264226424,
  "青森県 深浦町 北金ヶ沢駅": 264226488,
  "青森県 深浦町 深浦駅": 264226669,
  "青森県 深浦町 千畳敷駅": 264226725,
  "青森県 深浦町 陸奥柳田駅": 264227357,
  "青森県 深浦町 驫木駅": 264227359,
  "青森県 深浦町 白神岳登山口駅": 264227484,
  "青森県 深浦町 十二湖駅": 264227559,
  "青森県 深浦町 艫作駅": 264227563,
  "青森県 深浦町 ウェスパ椿山駅": 264227648,
  "青森県 深浦町 大間越駅": 264227686,
  "青森県 深浦町 松神駅": 264227688,
  "青森県 深浦町 横磯駅": 264227789,
  "青森県 深浦町 陸奥沢辺駅": 264227791,
  "青森県 深浦町 陸奥岩崎駅": 264228069
}