{
  "2559434145": {
    "en": "Chiba Prefecture Katori Omigawa Station",
    "ja": "千葉県 香取市 小見川駅"
  },
  "2559434150": {
    "en": "Chiba Prefecture Katori Sawara Station",
    "ja": "千葉県 香取市 佐原駅"
  },
  "2559434163": {
    "en": "Chiba Prefecture Katori Suigo Station",
    "ja": "千葉県 香取市 水郷駅"
  },
  "3012068699": {
    "en": "Chiba Prefecture Katori Oto Station",
    "ja": "千葉県 香取市 大戸駅"
  },
  "3012068712": {
    "en": "Chiba Prefecture Katori Katori Station",
    "ja": "千葉県 香取市 香取駅"
  },
  "3014683038": {
    "en": "Chiba Prefecture Katori Junikyo Station",
    "ja": "千葉県 香取市 十二橋駅"
  }
}