{
  "353690112": {
    "en": "Hokkaido Prefecture Chuo Hosui-Susukino Station",
    "ja": "北海道 中央区 豊水すすきの駅"
  },
  "4086807437": {
    "en": "Hokkaido Prefecture Chuo Naebo Station",
    "ja": "北海道 中央区 苗穂駅"
  },
  "5397731370": {
    "en": "Hokkaido Prefecture Chuo Sapporo Station",
    "ja": "北海道 中央区 さっぽろ駅"
  },
  "6060517713": {
    "en": "Hokkaido Prefecture Chuo Sōen Station",
    "ja": "北海道 中央区 桑園駅"
  },
  "6516226625": {
    "en": "Hokkaido Prefecture Chuo Odori Station",
    "ja": "北海道 中央区 大通駅"
  },
  "7805229110": {
    "en": "Hokkaido Prefecture Chuo Nakajima-Koen Station",
    "ja": "北海道 中央区 中島公園駅"
  },
  "7805229111": {
    "en": "Hokkaido Prefecture Chuo Susukino Station",
    "ja": "北海道 中央区 すすきの駅"
  },
  "7805229112": {
    "en": "Hokkaido Prefecture Chuo Odori Station",
    "ja": "北海道 中央区 大通駅"
  },
  "7805229113": {
    "en": "Hokkaido Prefecture Chuo Sapporo Station",
    "ja": "北海道 中央区 さっぽろ駅"
  },
  "7805229119": {
    "en": "Hokkaido Prefecture Chuo Horohira-Bashi Station",
    "ja": "北海道 中央区 幌平橋駅"
  },
  "7809484248": {
    "en": "Hokkaido Prefecture Chuo Nishi-28-Chome Station",
    "ja": "北海道 中央区 西28丁目駅"
  },
  "7809484249": {
    "en": "Hokkaido Prefecture Chuo Maruyama-Koen Station",
    "ja": "北海道 中央区 円山公園駅"
  },
  "7809484250": {
    "en": "Hokkaido Prefecture Chuo Nishi-18-Chome Station",
    "ja": "北海道 中央区 西18丁目駅"
  },
  "7809484251": {
    "en": "Hokkaido Prefecture Chuo Nishi-11-Chome Station",
    "ja": "北海道 中央区 西11丁目駅"
  },
  "7809484252": {
    "en": "Hokkaido Prefecture Chuo Odori Station",
    "ja": "北海道 中央区 大通駅"
  },
  "7809484253": {
    "en": "Hokkaido Prefecture Chuo Bus Center-Mae Station",
    "ja": "北海道 中央区 バスセンター前駅"
  }
}