{
  "愛知県 一宮市 木曽川駅": 3999572950,
  "愛知県 一宮市 尾張一宮駅": 3999573160,
  "愛知県 一宮市 新木曽川駅": 4919941785,
  "愛知県 一宮市 名鉄一宮駅": 8097840743,
  "愛知県 一宮市 黒田駅": 8099827852,
  "愛知県 一宮市 木曽川堤駅": 8099827854,
  "愛知県 一宮市 今伊勢駅": 8100500211,
  "愛知県 一宮市 石刀駅": 8100500213,
  "愛知県 一宮市 玉野駅": 8108143563,
  "愛知県 一宮市 萩原駅": 8108143566,
  "愛知県 一宮市 二子駅": 8108143568,
  "愛知県 一宮市 苅安賀駅": 8108143569,
  "愛知県 一宮市 観音寺駅": 8108143571,
  "愛知県 一宮市 西一宮駅": 8108143572,
  "愛知県 一宮市 開明駅": 8108143573,
  "愛知県 一宮市 奥町駅": 8108143574,
  "愛知県 一宮市 玉ノ井駅": 8108143577,
  "愛知県 一宮市 島氏永駅": 8108665370,
  "愛知県 一宮市 妙興寺駅": 8108665371
}