{
  "Ibaraki Prefecture Kasumigaura": 2682889,
  "Ibaraki Prefecture Tsukubamirai": 2682890,
  "Ibaraki Prefecture Tsukuba": 2682891,
  "Ibaraki Prefecture Hitachinaka": 2682892,
  "Ibaraki Prefecture Shimotsuma": 2682893,
  "Ibaraki Prefecture Goka": 2682894,
  "Ibaraki Prefecture Yachiyo": 2682895,
  "Ibaraki Prefecture Tone": 2682896,
  "Ibaraki Prefecture Kitaibaraki": 2682897,
  "Ibaraki Prefecture Toride": 2682898,
  "Ibaraki Prefecture Koga": 2682899,
  "Ibaraki Prefecture Tsuchiura": 2682900,
  "Ibaraki Prefecture Bando": 2682901,
  "Ibaraki Prefecture Shirosato": 2682902,
  "Ibaraki Prefecture Sakai": 2682903,
  "Ibaraki Prefecture Daigo": 2682904,
  "Ibaraki Prefecture Oarai": 2682905,
  "Ibaraki Prefecture Moriya": 2682906,
  "Ibaraki Prefecture Omitama": 2682907,
  "Ibaraki Prefecture Joso": 2682908,
  "Ibaraki Prefecture Hitachiomiya": 2682909,
  "Ibaraki Prefecture Hitachiota": 2682910,
  "Ibaraki Prefecture Hitachi": 2682911,
  "Ibaraki Prefecture Tokai": 2682912,
  "Ibaraki Prefecture Sakuragawa": 2682913,
  "Ibaraki Prefecture Mito": 2682914,
  "Ibaraki Prefecture Kawachi": 2682915,
  "Ibaraki Prefecture Itako": 2682916,
  "Ibaraki Prefecture Ushiku": 2682917,
  "Ibaraki Prefecture Ishioka": 2682918,
  "Ibaraki Prefecture Kamisu": 2682919,
  "Ibaraki Prefecture Inashiki": 2682920,
  "Ibaraki Prefecture Kasama": 2682921,
  "Ibaraki Prefecture Chikusei": 2682922,
  "Ibaraki Prefecture Yuki": 2682923,
  "Ibaraki Prefecture Miho": 2682924,
  "Ibaraki Prefecture Ibaraki": 2682925,
  "Ibaraki Prefecture Namekata": 2682926,
  "Ibaraki Prefecture Naka": 2682927,
  "Ibaraki Prefecture Hokota": 2682928,
  "Ibaraki Prefecture Ami": 2682929,
  "Ibaraki Prefecture Takahagi": 2682930,
  "Ibaraki Prefecture Kashima": 2682931,
  "Ibaraki Prefecture Ryugasaki": 2682932
}