{
  "264418849": {
    "en": "Hokkaido Prefecture Hokuto Kiyokawaguchi Station",
    "ja": "北海道 北斗市 清川口駅"
  },
  "264418851": {
    "en": "Hokkaido Prefecture Hokuto Kamiiso Station",
    "ja": "北海道 北斗市 上磯駅"
  },
  "264419325": {
    "en": "Hokkaido Prefecture Hokuto Moheji Station",
    "ja": "北海道 北斗市 茂辺地駅"
  },
  "264420644": {
    "en": "Hokkaido Prefecture Hokuto Higashi-Kunebetsu Station",
    "ja": "北海道 北斗市 東久根別駅"
  },
  "264421027": {
    "en": "Hokkaido Prefecture Hokuto Kunibetsu Station",
    "ja": "北海道 北斗市 久根別駅"
  },
  "264421043": {
    "en": "Hokkaido Prefecture Hokuto Nanaehama Station",
    "ja": "北海道 北斗市 七重浜駅"
  },
  "264421183": {
    "en": "Hokkaido Prefecture Hokuto Oshima-Tōbetsu Station",
    "ja": "北海道 北斗市 渡島当別駅"
  },
  "264428954": {
    "en": "Hokkaido Prefecture Hokuto Shin-Hakodate-Hokuto Station",
    "ja": "北海道 北斗市 新函館北斗駅"
  }
}