{
  "263180531": {
    "en": "Akita Prefecture Yokote Daigo Station",
    "ja": "秋田県 横手市 醍醐駅"
  },
  "264256216": {
    "en": "Akita Prefecture Yokote Kurosawa Station",
    "ja": "秋田県 横手市 黒沢駅"
  },
  "264256438": {
    "en": "Akita Prefecture Yokote Komatsukawa Station",
    "ja": "秋田県 横手市 小松川駅"
  },
  "264257118": {
    "en": "Akita Prefecture Yokote Yabitsu Station",
    "ja": "秋田県 横手市 矢美津駅"
  },
  "264257399": {
    "en": "Akita Prefecture Yokote Hiraishi Station",
    "ja": "秋田県 横手市 平石駅"
  },
  "264257461": {
    "en": "Akita Prefecture Yokote Ainono Station",
    "ja": "秋田県 横手市 相野々駅"
  },
  "6055012370": {
    "en": "Akita Prefecture Yokote Yokote Station",
    "ja": "秋田県 横手市 横手駅"
  },
  "7051942364": {
    "en": "Akita Prefecture Yokote Jumonji Station",
    "ja": "秋田県 横手市 十文字駅"
  },
  "7465108212": {
    "en": "Akita Prefecture Yokote Yanagita Station",
    "ja": "秋田県 横手市 柳田駅"
  }
}