{
  "265840237": {
    "en": "Miyazaki Prefecture Miyazaki Kibana Station",
    "ja": "宮崎県 宮崎市 木花駅"
  },
  "265840399": {
    "en": "Miyazaki Prefecture Miyazaki Kodomonokuni Station",
    "ja": "宮崎県 宮崎市 子供の国駅"
  },
  "265840829": {
    "en": "Miyazaki Prefecture Miyazaki Kouchiumi Station",
    "ja": "宮崎県 宮崎市 小内海駅"
  },
  "265841028": {
    "en": "Miyazaki Prefecture Miyazaki Minamikata Station",
    "ja": "宮崎県 宮崎市 南方駅"
  },
  "265841035": {
    "en": "Miyazaki Prefecture Miyazaki Aoshima Station",
    "ja": "宮崎県 宮崎市 青島駅"
  },
  "265841069": {
    "en": "Miyazaki Prefecture Miyazaki Oryūzako Station",
    "ja": "宮崎県 宮崎市 折生迫駅"
  },
  "265841135": {
    "en": "Miyazaki Prefecture Miyazaki Sosanji Station",
    "ja": "宮崎県 宮崎市 曽山寺駅"
  },
  "265842809": {
    "en": "Miyazaki Prefecture Miyazaki Uchiumi Station",
    "ja": "宮崎県 宮崎市 内海駅"
  },
  "265842911": {
    "en": "Miyazaki Prefecture Miyazaki Undōkōen Station",
    "ja": "宮崎県 宮崎市 運動公園駅"
  },
  "265848024": {
    "en": "Miyazaki Prefecture Miyazaki Kano Station",
    "ja": "宮崎県 宮崎市 加納駅"
  },
  "265848361": {
    "en": "Miyazaki Prefecture Miyazaki Hyuga-Sumiyoshi Station",
    "ja": "宮崎県 宮崎市 日向住吉駅"
  },
  "265848384": {
    "en": "Miyazaki Prefecture Miyazaki Sadowara Station",
    "ja": "宮崎県 宮崎市 佐土原駅"
  },
  "265848402": {
    "en": "Miyazaki Prefecture Miyazaki Kiyotake Station",
    "ja": "宮崎県 宮崎市 清武駅"
  },
  "265848405": {
    "en": "Miyazaki Prefecture Miyazaki Hasugaike Station",
    "ja": "宮崎県 宮崎市 蓮ヶ池駅"
  },
  "265848751": {
    "en": "Miyazaki Prefecture Miyazaki Tano Station",
    "ja": "宮崎県 宮崎市 田野駅"
  },
  "265849010": {
    "en": "Miyazaki Prefecture Miyazaki Miyazaki-Jingu Station",
    "ja": "宮崎県 宮崎市 宮崎神宮駅"
  },
  "265849089": {
    "en": "Miyazaki Prefecture Miyazaki Hyūga-Kutsukake Station",
    "ja": "宮崎県 宮崎市 日向沓掛駅"
  },
  "265889650": {
    "en": "Miyazaki Prefecture Miyazaki Miyazaki Airport Station",
    "ja": "宮崎県 宮崎市 宮崎空港駅"
  },
  "4008342859": {
    "en": "Miyazaki Prefecture Miyazaki Minami-Miyazaki Station",
    "ja": "宮崎県 宮崎市 南宮崎駅"
  },
  "4008342860": {
    "en": "Miyazaki Prefecture Miyazaki Tayoshi Station",
    "ja": "宮崎県 宮崎市 田吉駅"
  },
  "5726627473": {
    "en": "Miyazaki Prefecture Miyazaki Miyazaki Station",
    "ja": "宮崎県 宮崎市 宮崎駅"
  }
}